{
    "transactionHeader": {
      "tipVersion": "string",
      "transactionId": {
        "transactionId": "string",
        "transactionType": "New",
        "sourceId": "string",
        "sourceName": "string"
      },
      "originalTransactionId": {
        "transactionId": "string",
        "transactionType": "New",
        "sourceId": "string",
        "sourceName": "string"
      },
      "timeStamp": "2020-07-01T19:17:28Z"
    },
    "referenceIds": [
      {
        "referenceSourceName": "string",
        "referenceSourceId": "string",
        "referenceSourceLookup": "string",
        "referenceType": "RFP",
        "referenceId": 0,
        "referenceVersionId": "string",
        "referenceName": "string"
      }
    ],
    "orderBookedDate": "2020-07-01",
    "buyer": {
      "buyerId": "string",
      "buyerName": "string",
      "buyerReference": "string"
    },
    "commission": 0,
    "advertiser": {
      "advertiserId": "string",
      "advertiserName": "string",
      "advertiserReference": "string"
    },
    "brand": {
      "brandId": "string",
      "brandName": "string",
      "brandReference": "string"
    },
    "product": {
      "productId": "string",
      "productName": "string",
      "productReference": "string"
    },
    "cpeCode": {
      "clientCode": "string",
      "productCode": "string",
      "estimateCode": "string"
    },
    "contacts": [
      {
        "contactType": "Account Executive",
        "referenceSourceName": "string",
        "referenceSourceId": "string",
        "contactFirstName": "string",
        "contactLastName": "string",
        "addressLine1": "string",
        "addressLine2": "string",
        "city": "string",
        "state": "string",
        "postalCode": "string",
        "country": "string",
        "phoneNumber": "string",
        "email": "user@example.com",
        "effectiveDate": "2020-07-01"
      }
    ],
    "revenueType": "Cash",
    "businessType": "string",
    "localNational": "Local",
    "dealYear": 0,
    "calendarType": "Broadcast",
    "billingOption": {
      "billingCalendar": "Broadcast",
      "billingCycle": "Month",
      "billingGranularity": "Order"
    },
    "equivalized": true,
    "dateWindow": [
      {
        "startDate": "2020-07-01",
        "endDate": "2020-07-01"
      }
    ],
    "cancellationTerms": {
      "cancellationType": "Quarterly",
      "cancellation": "string",
      "cancellationPriorDays": 0,
      "cancellationPercentage": 0
    },
    "timeSeparations": [
      {
        "unitLength": 0,
        "timeSeparation": 0
      }
    ],
    "termsOfSales": "string",
    "externalComment": "string",
    "rateCard": {
      "rateCardId": "string",
      "rateCardName": "string"
    },
    "currency": "USD",
    "mediaOutlets": [
      {
        "mediaOutletId": "string",
        "mediaOutletName": "string",
        "mediaOutletType": "Broadcast TV",
        "mediaOutletChannel": "string",
        "mediaOutletMarketName": "string",
        "mediaOutletReference": "string"
      }
    ],
    "audienceSegments": [
      {
        "mediaOutletId": "string",
        "audienceSegment": {
          "audienceSegmentId": "string",
          "audienceSegmentName": "string",
          "audienceSegmentReference": "string",
          "audienceMethodology": "string",
          "primaryIndicator": true,
          "guarantee": true,
          "ratingSource": "Nielsen",
          "ratingStream": "Program Live"
        },
        "universes": [
          {
            "universeType": "Market",
            "universeTypeValue": 0
          }
        ]
      }
    ],
    "salesElements": [
      {
        "salesElement": {
          "mediaOutletId": "string",
          "salesElementName": "string",
          "salesElementId": "string",
          "salesElementType": "Time-specific"
        },
        "timePeriods": [
          {
            "dateWindow": {
              "startDate": "2020-07-01",
              "endDate": "2020-07-01"
            },
            "DOW": {
              "monday": true,
              "tuesday": true,
              "wednesday": true,
              "thursday": true,
              "friday": true,
              "saturday": true,
              "sunday": true
            },
            "timeWindow": {
              "startTime": "string",
              "endTime": "string"
            }
          }
        ],
        "programs": [
          "string"
        ],
        "salesElementTransactionInventory": [
          {
            "lineNum": "string",
            "lineReference": "string",
            "inventoryType": "Commercial",
            "linkType": {
              "linkType": "Billboard",
              "linkNum": 0,
              "linkSeq": 0
            },
            "inventoryPosition": "First",
            "inventoryLength": 0,
            "adu": true,
            "bonus": true,
            "salesElementTransactionDates": [
              {
                "dateType": "Week",
                "calendarType": "Broadcast",
                "dateWindow": {
                  "startDate": "2020-07-01",
                  "endDate": "2020-07-01"
                },
                "unitCount": 0,
                "dailyUnitDistribution": {
                  "monday": 0,
                  "tuesday": 0,
                  "wednesday": 0,
                  "thursday": 0,
                  "friday": 0,
                  "saturday": 0,
                  "sunday": 0
                },
                "rate": 0,
                "audiencesPricingMetrics": [
                  {
                    "audienceSegmentId": "string",
                    "audienceMetric": {
                      "audienceMetric": "Impressions",
                      "audienceMetricValue": 0
                    },
                    "pricingMetric": {
                      "pricingMetric": "CPM",
                      "pricingMetricValue": 0
                    }
                  }
                ]
              }
            ]
          }
        ]
      }
    ]
  }